neon_diana_utils/__init__.py
neon_diana_utils/cli.py
neon_diana_utils/configuration.py
neon_diana_utils/kubernetes_utils.py
neon_diana_utils/rabbitmq_api.py
neon_diana_utils/version.py
neon_diana_utils/helm_charts/diana-backend/Chart.yaml
neon_diana_utils/helm_charts/diana-backend/values.yaml
neon_diana_utils/helm_charts/diana-backend/templates/_helpers.tpl
neon_diana_utils/helm_charts/diana-backend/templates/config-secret.yaml
neon_diana_utils/helm_charts/diana-backend/templates/letsencrypt-issuer.yaml
neon_diana_utils/helm_charts/diana-backend/templates/rabbitmq-secret.yaml
neon_diana_utils/helm_charts/diana-backend/templates/tests/test-connection.yaml
neon_diana_utils/helm_charts/http-services/Chart.yaml
neon_diana_utils/helm_charts/http-services/values.yaml
neon_diana_utils/helm_charts/http-services/charts/base-http/Chart.yaml
neon_diana_utils/helm_charts/http-services/charts/base-http/templates/_deployment.tpl
neon_diana_utils/helm_charts/http-services/charts/base-http/templates/_domain.tpl
neon_diana_utils/helm_charts/http-services/charts/base-http/templates/_ingress.tpl
neon_diana_utils/helm_charts/http-services/charts/base-http/templates/_service.tpl
neon_diana_utils/helm_charts/http-services/charts/libretranslate/Chart.yaml
neon_diana_utils/helm_charts/http-services/charts/libretranslate/values.yaml
neon_diana_utils/helm_charts/http-services/charts/libretranslate/templates/NOTES.txt
neon_diana_utils/helm_charts/http-services/charts/libretranslate/templates/_helpers.tpl
neon_diana_utils/helm_charts/http-services/charts/libretranslate/templates/deployment.yaml
neon_diana_utils/helm_charts/http-services/charts/libretranslate/templates/ingress.yaml
neon_diana_utils/helm_charts/http-services/charts/libretranslate/templates/service.yaml
neon_diana_utils/helm_charts/http-services/charts/libretranslate/templates/tests/test-connection.yaml
neon_diana_utils/helm_charts/http-services/charts/tts-coqui/Chart.yaml
neon_diana_utils-1.0.0.dist-info/LICENSE.md
neon_diana_utils-1.0.0.dist-info/METADATA
neon_diana_utils-1.0.0.dist-info/WHEEL
neon_diana_utils-1.0.0.dist-info/entry_points.txt
neon_diana_utils-1.0.0.dist-info/top_level.txt
neon_diana_utils-1.0.0.dist-info/zip-safe
neon_diana_utils-1.0.0.dist-info/RECORD
