Metadata-Version: 2.1
Name: neon-diana-utils
Version: 1.0.0
Summary: Utilities for administration of Neon DIANA
Home-page: https://github.com/NeonGeckoCom/neon-diana-backend
Author: NeonGecko
Author-email: developers@neon.ai
License: BSD-3-Clause
Classifier: Intended Audience :: Developers
Classifier: Programming Language :: Python :: 3.6
License-File: LICENSE.md
Requires-Dist: requests (~=2.26)
Requires-Dist: pyyaml (~=5.4)
Requires-Dist: docker (~=5.0)
Requires-Dist: click (~=8.0)
Requires-Dist: click-default-group (~=1.2)
Requires-Dist: neon-mq-connector (>=0.6.1a9,~=0.3)
